{
  "_class": "group",
  "do_objectID": "D9F2C087-70F2-477F-B163-5DBBAAADF1B4",
  "exportOptions": {
    "_class": "exportOptions",
    "exportFormats": [
    ],
    "includedLayerIds": [
    ],
    "layerOptions": 0,
    "shouldTrim": false
  },
  "frame": {
    "_class": "rect",
    "constrainProportions": false,
    "height": 691,
    "width": 340,
    "x": 390,
    "y": 69
  },
  "hasClickThrough": false,
  "isFlippedHorizontal": false,
  "isFlippedVertical": false,
  "isLocked": false,
  "isVisible": true,
  "layerListExpandedType": 1,
  "layers": [
    {
      "class": "group",
      "id": "2396A427-AF4B-4B89-8554-F7A5EBE0FF43"
    },
    {
      "class": "group",
      "id": "103C0FC2-114B-472E-8E8A-933684B0405C"
    },
    {
      "class": "shapeGroup",
      "id": "280FAA54-FDAE-4B62-904E-F0276F8643DA"
    },
    {
      "class": "shapeGroup",
      "id": "20F54E8D-9958-4E36-81A9-9C55FBB1A7A8"
    }
  ],
  "name": "phone",
  "nameIsFixed": true,
  "resizingConstraint": 63,
  "resizingType": 0,
  "rotation": 0,
  "shouldBreakMaskChain": false,
  "style": {
    "_class": "style",
    "blur": {
      "_class": "blur",
      "center": "{0.5, 0.5}",
      "isEnabled": false,
      "motionAngle": 0,
      "radius": 6,
      "type": 0
    },
    "endDecorationType": 0,
    "miterLimit": 10,
    "startDecorationType": 0
  }
}